optimus_ids/__init__.py
python_optimus-1.0.1.dist-info/LICENSE
python_optimus-1.0.1.dist-info/METADATA
python_optimus-1.0.1.dist-info/WHEEL
python_optimus-1.0.1.dist-info/top_level.txt
python_optimus-1.0.1.dist-info/RECORD
