Metadata-Version: 2.1
Name: python-optimus
Version: 1.0.1
Summary: Transform internal id's to obfuscated integers using Knuth's integer hash
Home-page: https://github.com/mpcabd/python-optimus
Author: Abdullah Diab
Author-email: mpcabd@gmail.com
Maintainer: Abdullah Diab
Maintainer-email: mpcabd@gmail.com
License: MIT
Keywords: hashing hashids optimus knuth
Platform: ALL
Classifier: Programming Language :: Python :: 3
Classifier: License :: OSI Approved :: MIT License
Classifier: Operating System :: OS Independent
Requires-Python: >=3.8
